viphl/__init__.py
viphl/utils.py
viphl/dto/__init__.py
viphl/dto/bypoint.cpython-312-darwin.so
viphl/dto/hl.cpython-312-darwin.so
viphl/dto/recovery_window.cpython-312-darwin.so
viphl/dto/settings.cpython-312-darwin.so
viphl/dto/viphl.cpython-312-darwin.so
viphl-1.0.1.dist-info/METADATA
viphl-1.0.1.dist-info/WHEEL
viphl-1.0.1.dist-info/top_level.txt
viphl-1.0.1.dist-info/RECORD
